agent_redis_framework/__init__.py
agent_redis_framework/env.py
agent_redis_framework/helper.py
agent_redis_framework/redis_client.py
agent_redis_framework/utils.py
agent_redis_framework/hashes/__init__.py
agent_redis_framework/hashes/hash_client.py
agent_redis_framework/sortedset/__init__.py
agent_redis_framework/sortedset/sorted_queue.py
agent_redis_framework/streams/__init__.py
agent_redis_framework/streams/stream_client.py
agent_redis_framework-1.5.6.dist-info/METADATA
agent_redis_framework-1.5.6.dist-info/WHEEL
agent_redis_framework-1.5.6.dist-info/RECORD
