Metadata-Version: 2.4
Name: agent-redis-framework
Version: 1.5.6
Summary: A clean, elegant Python library for Redis-based multi-task scheduling with SortedSets and Streams.
Requires-Python: >=3.10
Requires-Dist: redis<=7.1.0,>=7.0.0
Requires-Dist: typing-extensions>=4.15.0
Provides-Extra: dev
Requires-Dist: fastapi>=0.127.0; extra == 'dev'
Requires-Dist: pydantic>=2.12.5; extra == 'dev'
Requires-Dist: pytest<9.0,>=8.0; extra == 'dev'
Requires-Dist: uvicorn[standard]>=0.40.0; extra == 'dev'
